nerre_weather/__init__.py
nerre_weather/cli.py
nerre_weather/core.py
nerre_weather-0.1.0.dist-info/METADATA
nerre_weather-0.1.0.dist-info/WHEEL
nerre_weather-0.1.0.dist-info/entry_points.txt
nerre_weather-0.1.0.dist-info/top_level.txt
nerre_weather-0.1.0.dist-info/RECORD
