Metadata-Version: 2.4
Name: nerre_weather
Version: 0.1.0
Summary: Nerre multi-city weather CLI with charts and CSV export
Author-email: Nerre <your.email@example.com>
Requires-Python: >=3.9
Requires-Dist: requests
Requires-Dist: tabulate
Requires-Dist: matplotlib
Requires-Dist: colorama
